bashmocker/__init__.py
bashmocker/bashmocker.py
bashmocker-0.3.0.dist-info/LICENSE
bashmocker-0.3.0.dist-info/METADATA
bashmocker-0.3.0.dist-info/WHEEL
bashmocker-0.3.0.dist-info/top_level.txt
bashmocker-0.3.0.dist-info/RECORD
