Metadata-Version: 2.1
Name: bashmocker
Version: 0.3.0
Summary: A Python helper for unit testing shell scripts.
Home-page: https://github.com/EdinburghGenomics/bashmocker
Author: Timothy Booth
Author-email: tim.booth@ed.ac.uk
License: UNKNOWN
Project-URL: Bug Tracker, https://github.com/EdinburghGenomics/bashmocker/issues
Platform: UNKNOWN
Classifier: Programming Language :: Python :: 3
Classifier: License :: OSI Approved :: MIT License
Classifier: Operating System :: POSIX
Requires-Python: >=3.6
License-File: LICENSE
